fedmind/__init__.py
fedmind/config.py
fedmind/data.py
fedmind/server.py
fedmind/utils.py
fedmind/algs/__init__.py
fedmind/algs/fedavg.py
fedmind/algs/fedprox.py
fedmind/algs/mfl.py
fedmind-0.2.2.dist-info/METADATA
fedmind-0.2.2.dist-info/WHEEL
fedmind-0.2.2.dist-info/entry_points.txt
fedmind-0.2.2.dist-info/licenses/LICENSE
fedmind-0.2.2.dist-info/RECORD
