Metadata-Version: 2.4
Name: fedmind
Version: 0.2.2
Summary: Federated Learning research framework in your mind
Project-URL: Homepage, https://github.com/Xiao-Chenguang/FedMind
Project-URL: Releases, https://github.com/Xiao-Chenguang/FedMind/releases
Project-URL: Issues, https://github.com/Xiao-Chenguang/FedMind/issues
Author-email: Xiao Chenguang <xiaochenguang0719@qq.com>
License: MIT License
License-File: LICENSE
Keywords: federated-learning,framework,research
Classifier: Development Status :: 3 - Alpha
Classifier: Intended Audience :: Developers
Classifier: Intended Audience :: Education
Classifier: Intended Audience :: Science/Research
Classifier: License :: OSI Approved :: MIT License
Classifier: Programming Language :: Python :: 3
Classifier: Programming Language :: Python :: 3.12
Classifier: Programming Language :: Python :: 3.13
Requires-Python: >=3.12
Requires-Dist: numpy>=2.1.2
Requires-Dist: torch>=2.4.1
Requires-Dist: wandb>=0.18.5
